Happypanda-1.1.dist-info/DESCRIPTION.rst
Happypanda-1.1.dist-info/LICENSE.txt
Happypanda-1.1.dist-info/METADATA
Happypanda-1.1.dist-info/RECORD
Happypanda-1.1.dist-info/WHEEL
Happypanda-1.1.dist-info/entry_points.txt
Happypanda-1.1.dist-info/metadata.json
Happypanda-1.1.dist-info/top_level.txt
happypanda/__init__.py
happypanda/__main__.py
happypanda/app.py
happypanda/app_constants.py
happypanda/asm_manager.py
happypanda/color_line_edit.py
happypanda/executors.py
happypanda/fetch.py
happypanda/gallery.py
happypanda/gallerydb.py
happypanda/gallerydialog.py
happypanda/hplugins.py
happypanda/io_misc.py
happypanda/misc.py
happypanda/misc_db.py
happypanda/pewnet.py
happypanda/settings.py
happypanda/settingsdialog.py
happypanda/utils.py
happypanda/database/__init__.py
happypanda/database/arguments.py
happypanda/database/db.py
happypanda/database/db_constants.py
happypanda/res/gallery_def_ico.ico
happypanda/res/happypanda.ico
happypanda/res/happypanda.png
happypanda/res/license.txt
happypanda/res/settings.png
happypanda/res/style.css
