Metadata-Version: 2.0
Name: Happypanda
Version: 1.1
Summary: A cross platform manga/doujinshi manager with namespace & tag support
Home-page: https://github.com/Pewpews/happypanda
Author: Pewpew
Author-email: pew@pewpew.moe
License: GPLv2+
Keywords: manga,doujinshi,downloader,management,cross-platform
Platform: UNKNOWN
Classifier: Development Status :: 5 - Production/Stable
Classifier: Intended Audience :: End Users/Desktop
Classifier: Topic :: Database :: Front-Ends
Classifier: License :: OSI Approved :: GNU General Public License v2 or later (GPLv2+)
Classifier: Programming Language :: Python :: 3
Classifier: Programming Language :: Python :: 3.4
Classifier: Programming Language :: Python :: 3.5
Classifier: Programming Language :: Python :: 3.6
Requires-Dist: QtAwesome
Requires-Dist: Send2Trash
Requires-Dist: appdirs
Requires-Dist: beautifulsoup4
Requires-Dist: pillow
Requires-Dist: python-dateutil
Requires-Dist: rarfile
Requires-Dist: requests
Requires-Dist: robobrowser
Requires-Dist: scandir
Requires-Dist: watchdog
